MANIFEST.in
README.md
myisqueeze.py
pisqueeze
pisqueeze.sh
setup.py
isqueeze/SBClient.py
isqueeze/__init__.py
isqueeze/isqueeze.py
isqueeze/player.py
isqueeze/server.py
isqueeze.egg-info/PKG-INFO
isqueeze.egg-info/SOURCES.txt
isqueeze.egg-info/dependency_links.txt
isqueeze.egg-info/top_level.txt